pyjlyric/__init__.py
pyjlyric/base.py
pyjlyric/main.py
pyjlyric/model.py
pyjlyric/parse.py
pyjlyric/py.typed
pyjlyric/util.py
pyjlyric/animap/__init__.py
pyjlyric/animap/model.py
pyjlyric/animap/parser.py
pyjlyric/evesta/__init__.py
pyjlyric/evesta/model.py
pyjlyric/evesta/parser.py
pyjlyric/gakki/__init__.py
pyjlyric/gakki/model.py
pyjlyric/gakki/parser.py
pyjlyric/hoick/__init__.py
pyjlyric/hoick/model.py
pyjlyric/hoick/parser.py
pyjlyric/jlyric/__init__.py
pyjlyric/jlyric/model.py
pyjlyric/jlyric/parser.py
pyjlyric/joysound/__init__.py
pyjlyric/joysound/model.py
pyjlyric/joysound/parser.py
pyjlyric/jtotal/__init__.py
pyjlyric/jtotal/model.py
pyjlyric/jtotal/parser.py
pyjlyric/kashinavi/__init__.py
pyjlyric/kashinavi/model.py
pyjlyric/kashinavi/parser.py
pyjlyric/linkcore/__init__.py
pyjlyric/linkcore/model.py
pyjlyric/linkcore/parser.py
pyjlyric/musicbook/__init__.py
pyjlyric/musicbook/model.py
pyjlyric/musicbook/parser.py
pyjlyric/petitlyrics/__init__.py
pyjlyric/petitlyrics/model.py
pyjlyric/petitlyrics/parser.py
pyjlyric/utamap/__init__.py
pyjlyric/utamap/model.py
pyjlyric/utamap/parser.py
pyjlyric/utanet/__init__.py
pyjlyric/utanet/model.py
pyjlyric/utanet/parser.py
pyjlyric/utaten/__init__.py
pyjlyric/utaten/model.py
pyjlyric/utaten/parser.py
pyjlyric-1.3.2.dist-info/METADATA
pyjlyric-1.3.2.dist-info/WHEEL
pyjlyric-1.3.2.dist-info/entry_points.txt
pyjlyric-1.3.2.dist-info/licenses/LICENSE
pyjlyric-1.3.2.dist-info/RECORD
