Metadata-Version: 2.4
Name: pyjlyric
Version: 1.3.2
Summary: Japanese Lyric Aggregator
Project-URL: Repository, https://github.com/eggplants/pyjlyric
Author-email: eggplants <w10776e8w@yahoo.co.jp>
License: MIT
License-File: LICENSE
Keywords: download-lyrics,japanese,japanese-songs,lyrics,lyrics-scraping
Classifier: License :: OSI Approved :: MIT License
Classifier: Programming Language :: Python :: 3 :: Only
Classifier: Programming Language :: Python :: 3.9
Classifier: Programming Language :: Python :: 3.10
Classifier: Programming Language :: Python :: 3.11
Classifier: Programming Language :: Python :: 3.12
Classifier: Programming Language :: Python :: 3.13
Classifier: Typing :: Typed
Requires-Python: <4,>=3.9
Requires-Dist: beautifulsoup4<5,>=4.12.3
Requires-Dist: chardet<6,>=5.2
Requires-Dist: eval-type-backport<0.3,>=0.2.2; python_version < '3.10'
Requires-Dist: lxml<6,>=5.3
Requires-Dist: pydantic<3,>=2.10.5
Requires-Dist: requests<3,>=2.32.3
Requires-Dist: typing-extensions<5,>=4.12.2
